rsb_git/__init__.py
rsb_git/_git.py
rsb_git/_version.py
rsb_git-1.13.1.dist-info/LICENSE
rsb_git-1.13.1.dist-info/METADATA
rsb_git-1.13.1.dist-info/WHEEL
rsb_git-1.13.1.dist-info/top_level.txt
rsb_git-1.13.1.dist-info/RECORD
