Metadata-Version: 2.1
Name: rsb-git
Version: 1.13.1
Summary: High level interface for git functionality
License: License: Proprietary Rohde & Schwarz
Requires-Python: >=3.8
License-File: LICENSE
